h_anomaly/__init__.py
h_anomaly/bcluster.py
h_anomaly/birch.py
h_anomaly/driver.py
h_anomaly-0.0.6.dist-info/LICENSE
h_anomaly-0.0.6.dist-info/METADATA
h_anomaly-0.0.6.dist-info/WHEEL
h_anomaly-0.0.6.dist-info/top_level.txt
h_anomaly-0.0.6.dist-info/RECORD
